Metadata-Version: 2.1
Name: proj_pacote_processamento
Version: 0.1
Summary: Pacote para processamento de imagens
Author: Renan Azevedo
Author-email: renanazevedoofc_msc@outlook.com
Classifier: Programming Language :: Python :: 3
Classifier: License :: OSI Approved :: MIT License
Classifier: Operating System :: OS Independent
Requires-Python: >=3.6
Requires-Dist: numpy
Requires-Dist: matplotlib
Requires-Dist: scikit-image
